chronotrack/__init__.py
chronotrack/api.py
chronotrack/exceptions.py
chronotrack/utils.py
chronotrack-0.0.4.dist-info/METADATA
chronotrack-0.0.4.dist-info/RECORD
chronotrack-0.0.4.dist-info/WHEEL
chronotrack-0.0.4.dist-info/top_level.txt
